PythonFileLibrary/FileReader.py
PythonFileLibrary/RecursiveScanner.py
PythonFileLibrary/__init__.py
PythonFileLibrary/integration/FileReaderTest.py
PythonFileLibrary/integration/IntegrationTestRunner.py
PythonFileLibrary/integration/RecursiveScannerTest.py
PythonFileLibrary/integration/__init__.py
PythonFileLibrary/integration/__main__.py
PythonFileLibrary-1.0.1.dist-info/LICENSE
PythonFileLibrary-1.0.1.dist-info/METADATA
PythonFileLibrary-1.0.1.dist-info/WHEEL
PythonFileLibrary-1.0.1.dist-info/top_level.txt
PythonFileLibrary-1.0.1.dist-info/RECORD
