Metadata-Version: 2.1
Name: PythonFileLibrary
Version: 1.0.1
Summary: A small cross-platform file library in Python
Home-page: https://github.com/Desperationis/PythonFileLibrary
Author: Diego Contreras
Author-email: smarttdiego@gmail.com
License: UNKNOWN
Project-URL: Bug Tracker, https://github.com/Desperationis/PythonFileLibrary/issues
Platform: UNKNOWN
Classifier: Programming Language :: Python :: 3
Classifier: License :: OSI Approved :: MIT License
Classifier: Operating System :: OS Independent
Requires-Python: >=3.6
License-File: LICENSE
